LICENSE
MANIFEST.in
setup.py
customadmin/__init__.py
customadmin/admin.py
customadmin/conf.py
customadmin/models.py
customadmin/urls.py
customadmin/utils.py
customadmin/views.py
customadmin/static/customadmin/css/layout.css
customadmin/static/customadmin/images/default_app_icon.png
customadmin/static/customadmin/images/nav-bg.gif
customadmin/static/customadmin/images/tool-right.gif
customadmin/static/customadmin/images/tool-right_over.gif
customadmin/static/customadmin/images/upy_model.png
customadmin/static/customadmin/js/custommodel.js
customadmin/static/customadmin/js/global_admin.js
customadmin/template_context/__init__.py
customadmin/template_context/context_processors.py
customadmin/templates/customadmin.css.html
customadmin/templates/admin/admin_default.html
customadmin/templates/admin/app_index.html
customadmin/templates/admin/base.html
customadmin/templates/admin/base_site.html
customadmin/templates/admin/change_form.html
customadmin/templates/admin/change_list.html
customadmin/templates/admin/custom_admin_layout.html
customadmin/templates/admin/custom_index.html
customadmin/templates/admin/use_app_icons.html
customadmin/templates/admin/use_custom_app.html
customadmin/templates/admin/use_inner_model_icons.html
customadmin/templates/admin/use_model_icons.html
customadmin/templates/admin/use_total_model_icons.html
customadmin/templates/rosetta/base.html
customadmin/templates/rosetta/languages.html
customadmin/templates/rosetta/pofile.html
customadmin/templates/rosetta/css/rosetta.css
customadmin/templates/rosetta/js/rosetta.js
customadmin/templatetags/__init__.py
customadmin/templatetags/customadmin_tags.py
twentytab_customadmin.egg-info/PKG-INFO
twentytab_customadmin.egg-info/SOURCES.txt
twentytab_customadmin.egg-info/dependency_links.txt
twentytab_customadmin.egg-info/requires.txt
twentytab_customadmin.egg-info/top_level.txt