Metadata-Version: 1.0
Name: twentytab-customadmin
Version: 0.17
Summary: A django app to customize your admin interface with icons for applications and models and other stuffs
Home-page: https://github.com/20tab/twentytab-customadmin
Author: 20tab S.r.l.
Author-email: info@20tab.com
License: MIT License
Platform: UNKNOWN
